SimAnn/SimAnn.py
SimAnn/__init__.py
SimAnn-1.2.1.dist-info/METADATA
SimAnn-1.2.1.dist-info/WHEEL
SimAnn-1.2.1.dist-info/top_level.txt
SimAnn-1.2.1.dist-info/RECORD
