Metadata-Version: 2.1
Name: SimAnn
Version: 1.2.1
Summary: Simple Simulated Annealing curve fit algorithm
Home-page: https://github.com/gcorucci/Simple_Simulated_Annealing_curve_fit
Author: Giacomo Corucci
Author-email: giacomocorucci@virgilio.it
Requires-Dist: numpy
